CHANGELOG.rst
LICENSE.txt
MANIFEST.in
README.rst
config.yml
setup.py
config/config_polyfts.yml
config/config_polyorder.yml
config/config_pydiagram.yml
docs/tips.md
pydiagram/__init__.py
pydiagram/__main__.py
pydiagram/_version.py
pydiagram/accuracy.py
pydiagram/boundary.py
pydiagram/config.py
pydiagram/diagram.py
pydiagram/energy.py
pydiagram/io.py
pydiagram/plot.py
pydiagram/separation.py
pydiagram/server.py
pydiagram/settings.py
pydiagram/simulation.py
pydiagram/size.py
pydiagram/utils.py
pydiagram.egg-info/PKG-INFO
pydiagram.egg-info/SOURCES.txt
pydiagram.egg-info/dependency_links.txt
pydiagram.egg-info/entry_points.txt
pydiagram.egg-info/not-zip-safe
pydiagram.egg-info/requires.txt
pydiagram.egg-info/top_level.txt
tests/log.BCC
tests/log.DIS
tests/phase_diagram.dgm
tests/test.dgm
tests/test_accuracy.py
tests/test_boundary.py
tests/test_config.py
tests/test_diagram.py
tests/test_energy.py
tests/test_io.py
tests/test_plot.py
tests/test_separation.py
tests/test_server.py
tests/test_simulation.py
tests/test_size.py
tests/test_utils.py