Metadata-Version: 1.1
Name: pydiagram
Version: 0.6
Summary: PyDiagram is a python package for generating a phase diagram from results output by polymer field-theoretic simulations. PyDiagram also provides functions for analysis of simulation results.
Home-page: https://github.com/liuyxpp/pydiagram
Author: Yi-Xin Liu
Author-email: liuyxpp@gmail.com
License: BSD
Platform: UNKNOWN
Classifier: Development Status :: 4 - Beta
Classifier: Intended Audience :: Developers
Classifier: License :: OSI Approved :: BSD License
Classifier: Operating System :: OS Independent
Classifier: Programming Language :: Python
